dash_mdxeditor/MdxEditor.py
dash_mdxeditor/__init__.py
dash_mdxeditor/_imports_.py
dash_mdxeditor/dash_mdxeditor.min.js
dash_mdxeditor/dash_mdxeditor.min.js.map
dash_mdxeditor/metadata.json
dash_mdxeditor/package-info.json
dash_mdxeditor-0.0.1.dist-info/LICENSE
dash_mdxeditor-0.0.1.dist-info/METADATA
dash_mdxeditor-0.0.1.dist-info/WHEEL
dash_mdxeditor-0.0.1.dist-info/top_level.txt
dash_mdxeditor-0.0.1.dist-info/RECORD
