Metadata-Version: 2.1
Name: dash_mdxeditor
Version: 0.0.1
Summary: Dash wrapper for the MdxEditor React library
Author: Jose Gómez Gadea <jgomez@spendmatters.com>
License: MIT
Classifier: Framework :: Dash
License-File: LICENSE
